{
  "name": "錬金相の抽出、保存",
  "icon": "magitech:tourmaline",
  "category": "magitech:alchemical_aspect",
  "pages": [
    {
      "type": "patchouli:text",
      "text": "錬金術に必須となるエネルギーの形態。"
    },
    {
      "type": "patchouli:text",
      "title": "錬金相の抽出",
      "text": "錬金相はそれぞれの象徴する概念を持つ物体から抽出することができる。$(br2)少量が必要な場合は、水を使用するザルディウス錬金によって抽出できる。"
    },
    {
      "type": "patchouli:text",
      "title": "錬金相の保管",
      "text": "錬金相は不安定で危険なためそのままの状態で保管することはできないので、結晶に封入する形で保管される。$(br2)封入する結晶はトルマリンやクォーツが適していることが知られている。$(br2)また、結晶に封入された錬金相は概念を浸透させ、性質を変えてしまうため再利用は一切できない。"
    },
    {
      "type": "patchouli:text",
      "title": "少量の錬金相結晶の製法",
      "text": "ザルディウス錬金を使用して、以下の物質からそれぞれの錬金相結晶を抽出することができる。"
    },
    {
      "type": "magitech:zardius_crucible_recipe",
      "title": "item.magitech.ember_crystal",
      "recipe": "magitech:ember_crystal",
      "text": "熱を帯びた結晶。燃料から抽出できる。"
    },
    {
      "type": "magitech:zardius_crucible_recipe",
      "title": "item.magitech.glace_crystal",
      "recipe": "magitech:glace_crystal",
      "text": "周囲から成長する結晶。クリスタルから抽出できる。"
    },
    {
      "type": "magitech:zardius_crucible_recipe",
      "title": "item.magitech.surge_crystal",
      "recipe": "magitech:surge_crystal",
      "text": "点滅する結晶。金属から抽出できる。"
    },
    {
      "type": "magitech:zardius_crucible_recipe",
      "title": "item.magitech.phantom_crystal",
      "recipe": "magitech:phantom_crystal",
      "text": "すり抜ける結晶。半実在の物質から抽出できる。"
    },
    {
      "type": "magitech:zardius_crucible_recipe",
      "title": "item.magitech.tremor_crystal",
      "recipe": "magitech:tremor_crystal",
      "text": "震える結晶。岩石から抽出できる。"
    },
    {
      "type": "magitech:zardius_crucible_recipe",
      "title": "item.magitech.magic_crystal",
      "recipe": "magitech:magic_crystal",
      "text": "力を発する結晶。マナが染み込んだ物質から抽出できる。"
    },
    {
      "type": "magitech:zardius_crucible_recipe",
      "title": "item.magitech.flow_crystal",
      "recipe": "magitech:flow_crystal",
      "text": "風をまとう結晶。生物から抽出できる。"
    },
    {
      "type": "magitech:zardius_crucible_recipe",
      "title": "item.magitech.hollow_crystal",
      "recipe": "magitech:hollow_crystal",
      "text": "時間と空間を歪める結晶。虚無から抽出できる。"
    }
  ]
}